eloverblik/ElOverblik.py
eloverblik/__init__.py
ElOverblik-1.0.0.dist-info/LICENSE
ElOverblik-1.0.0.dist-info/METADATA
ElOverblik-1.0.0.dist-info/WHEEL
ElOverblik-1.0.0.dist-info/top_level.txt
ElOverblik-1.0.0.dist-info/RECORD
